sifr_benchmark/__init__.py
sifr_benchmark/capture.py
sifr_benchmark/capture_e2llm.py
sifr_benchmark/cli.py
sifr_benchmark/formats.py
sifr_benchmark/ground_truth.py
sifr_benchmark/models.py
sifr_benchmark/runner.py
sifr_benchmark/scoring.py
sifr_benchmark/verification.py
sifr_benchmark/verify.py
sifr_benchmark-0.1.39.dist-info/METADATA
sifr_benchmark-0.1.39.dist-info/WHEEL
sifr_benchmark-0.1.39.dist-info/entry_points.txt
sifr_benchmark-0.1.39.dist-info/licenses/LICENSE
sifr_benchmark-0.1.39.dist-info/RECORD
