Metadata-Version: 2.4
Name: sifr-benchmark
Version: 0.1.39
Summary: Benchmark for evaluating LLM understanding of web UI: SiFR vs HTML vs AXTree vs Screenshots
Project-URL: Homepage, https://github.com/Alechko375/sifr-benchmark
Project-URL: Documentation, https://github.com/Alechko375/sifr-benchmark#readme
Project-URL: Repository, https://github.com/Alechko375/sifr-benchmark
Project-URL: Issues, https://github.com/Alechko375/sifr-benchmark/issues
Author: SiFR Contributors
License-Expression: MIT
License-File: LICENSE
Keywords: accessibility,ai-agents,benchmark,llm,sifr,web-automation,web-ui
Classifier: Development Status :: 3 - Alpha
Classifier: Intended Audience :: Developers
Classifier: License :: OSI Approved :: MIT License
Classifier: Programming Language :: Python :: 3
Classifier: Programming Language :: Python :: 3.9
Classifier: Programming Language :: Python :: 3.10
Classifier: Programming Language :: Python :: 3.11
Classifier: Programming Language :: Python :: 3.12
Classifier: Topic :: Scientific/Engineering :: Artificial Intelligence
Classifier: Topic :: Software Development :: Testing
Requires-Python: >=3.9
Requires-Dist: anthropic>=0.20.0
Requires-Dist: click>=8.0.0
Requires-Dist: httpx>=0.25.0
Requires-Dist: openai>=1.0.0
Requires-Dist: playwright>=1.40.0
Requires-Dist: pyyaml>=6.0
Requires-Dist: rich>=13.0.0
Requires-Dist: tqdm>=4.65.0
Provides-Extra: capture
Requires-Dist: beautifulsoup4>=4.12.0; extra == 'capture'
Requires-Dist: playwright>=1.40.0; extra == 'capture'
Provides-Extra: dev
Requires-Dist: black>=23.0.0; extra == 'dev'
Requires-Dist: pytest-asyncio>=0.21.0; extra == 'dev'
Requires-Dist: pytest>=7.0.0; extra == 'dev'
Requires-Dist: ruff>=0.1.0; extra == 'dev'
